sabeel_test_pypi/__init__.py
sabeel_test_pypi/indextools.py
sabeel_test_pypi-0.0.2.dist-info/LICENSE.txt
sabeel_test_pypi-0.0.2.dist-info/METADATA
sabeel_test_pypi-0.0.2.dist-info/WHEEL
sabeel_test_pypi-0.0.2.dist-info/top_level.txt
sabeel_test_pypi-0.0.2.dist-info/RECORD
