Metadata-Version: 2.1
Name: sabeel-test-pypi
Version: 0.0.2
Summary: Useful tools to work with test
Home-page: https://github.com/sabeelmuttil/test-pypi
Author: Sabeel K M
Author-email: sabeelmuttil@gmail.com
License: MIT
Download-URL: https://pypi.org/project/sabeel-test-pypi/
Keywords: test,testpypi,testSearch
Platform: UNKNOWN
